nludb/__init__.py
nludb/classifier.py
nludb/embedding_index.py
nludb/file.py
nludb/models.py
nludb/nludb.py
nludb/tasks.py
nludb/api/base.py
nludb/examples/__init__.py
nludb/examples/anomaly_detection.py
nludb/examples/chatbot.py
nludb/types/__init__.py
nludb/types/async_task.py
nludb/types/base.py
nludb/types/block_types.py
nludb/types/classifier.py
nludb/types/classifier_models.py
nludb/types/embedding.py
nludb/types/embedding_index.py
nludb/types/embedding_models.py
nludb/types/file.py
nludb/types/file_formats.py
nludb/types/model.py
nludb/types/parsing.py
nludb/types/parsing_models.py
nludb/types/search.py
nludb-2.0.1.dist-info/AUTHORS.rst
nludb-2.0.1.dist-info/LICENSE.txt
nludb-2.0.1.dist-info/METADATA
nludb-2.0.1.dist-info/WHEEL
nludb-2.0.1.dist-info/top_level.txt
nludb-2.0.1.dist-info/RECORD
