Metadata-Version: 2.1
Name: nludb
Version: 2.0.1
Summary: NLUDB is a database that helps developers get work done with natural language content.
Home-page: https://github.com/pyscaffold/pyscaffold/
Author: Edward Benson
Author-email: ted@nludb.com
License: MIT
Project-URL: Documentation, https://pyscaffold.org/
Platform: any
Classifier: Development Status :: 4 - Beta
Classifier: Programming Language :: Python
License-File: LICENSE.txt
License-File: AUTHORS.rst
Requires-Dist: requests (>=2.2)
Requires-Dist: importlib-metadata ; python_version < "3.8"
Provides-Extra: testing
Requires-Dist: setuptools ; extra == 'testing'
Requires-Dist: pytest ; extra == 'testing'
Requires-Dist: pytest-cov ; extra == 'testing'
